{"cameraMode":{"drawMode":0,"name":"Shaded","section":"Shading Mode"},"sceneLighting":true,"audioPlay":false,"sceneViewState":{"m_AlwaysRefresh":false,"showFog":true,"showSkybox":true,"showFlares":true,"showImageEffects":true,"showParticleSystems":true,"showVisualEffectGraphs":true,"m_FxEnabled":true},"in2DMode":false,"pivot":{"x":3.763103485107422,"y":-1.779022216796875,"z":-1.7179336547851563},"rotation":{"x":-0.07584116607904434,"y":0.9241529107093811,"z":-0.26655444502830508,"w":-0.26294389367103579},"size":10.0,"orthographic":false}